{
  "datasets": [
    {
      "name": "home_tile_interactions_ctr_dataset",
      "displayName": "Home Tile Interactions CTR Dataset",
      "queryLines": [
        "SELECT\n  home_tile,\n  SUM(unique_tile_views) as unique_tile_views,\n  SUM(unique_tile_clicks) as unique_tile_clicks,\n  SUM(unique_interstitial_views) as unique_interstitial_views,\n  SUM(unique_interstitial_primary_button_clicks) as unique_interstitial_primary_button_clicks,\n  SUM(unique_interstitial_secondary_button_clicks) as unique_interstitial_secondary_button_clicks,\n  SUM(unique_tile_clicks) / SUM(unique_tile_views) as ctr,\n  SUM(unique_interstitial_primary_button_clicks) / SUM(unique_tile_views) as primary_button_clicked_vs_tile_displayed,\n  SUM(unique_interstitial_secondary_button_clicks) / SUM(unique_tile_views) as secondary_button_clicked_vs_tile_displayed,\n  SUM(unique_interstitial_primary_button_clicks) / NULLIF(SUM(unique_interstitial_views), 0) as primary_button_clicked_vs_interstitial_displayed,\n  SUM(unique_interstitial_secondary_button_clicks) / NULLIF(SUM(unique_interstitial_views), 0) as secondary_button_clicked_vs_interstitial_displayed\nFROM hpx_events_model_homepage_summary\nGROUP BY home_tile\nORDER BY unique_tile_views DESC"
      ]
    }
  ],
  "pages": [
    {
      "name": "home_tile_interactions_ctr_page",
      "displayName": "Home Tile Interactions CTR",
      "layout": [
        {
          "widget": {
            "name": "home_tile_interactions_ctr_counter",
            "queries": [
              {
                "name": "main_query",
                "query": {
                  "datasetName": "home_tile_interactions_ctr_dataset",
                  "fields": [
                    { "name": "ctr", "expression": "SUM(`unique_tile_clicks`) / SUM(`unique_tile_views`)" }
                  ],
                  "disaggregated": false
                }
              }
            ],
            "spec": {
              "version": 3,
              "widgetType": "counter",
              "encodings": {
                "value": {
                  "fieldName": "ctr",
                  "displayName": "Click-Through Rate",
                  "scale": { "type": "quantitative" },
                  "format": { "type": "percentage", "precision": 2 }
                }
              },
              "frame": {
                "title": "Overall Home Tile CTR",
                "showTitle": true
              }
            }
          },
          "position": { "x": 0, "y": 0, "width": 6, "height": 4 }
        },
        {
          "widget": {
            "name": "home_tile_interactions_ctr_table",
            "queries": [
              {
                "name": "main_query",
                "query": {
                  "datasetName": "home_tile_interactions_ctr_dataset",
                  "fields": [
                    { "name": "home_tile", "expression": "`home_tile`" },
                    { "name": "unique_tile_views", "expression": "`unique_tile_views`" },
                    { "name": "unique_tile_clicks", "expression": "`unique_tile_clicks`" },
                    { "name": "ctr", "expression": "`ctr`" },
                    { "name": "unique_interstitial_views", "expression": "`unique_interstitial_views`" },
                    { "name": "unique_interstitial_primary_button_clicks", "expression": "`unique_interstitial_primary_button_clicks`" },
                    { "name": "unique_interstitial_secondary_button_clicks", "expression": "`unique_interstitial_secondary_button_clicks`" },
                    { "name": "primary_button_clicked_vs_tile_displayed", "expression": "`primary_button_clicked_vs_tile_displayed`" },
                    { "name": "secondary_button_clicked_vs_tile_displayed", "expression": "`secondary_button_clicked_vs_tile_displayed`" },
                    { "name": "primary_button_clicked_vs_interstitial_displayed", "expression": "`primary_button_clicked_vs_interstitial_displayed`" },
                    { "name": "secondary_button_clicked_vs_interstitial_displayed", "expression": "`secondary_button_clicked_vs_interstitial_displayed`" }
                  ],
                  "disaggregated": false
                }
              }
            ],
            "spec": {
              "version": 3,
              "widgetType": "table",
              "encodings": {
                "columns": [
                  {
                    "fieldName": "home_tile",
                    "displayName": "Home Tile",
                    "scale": { "type": "categorical" }
                  },
                  {
                    "fieldName": "unique_tile_views",
                    "displayName": "Unique Tile Views",
                    "scale": { "type": "quantitative" },
                    "format": { "type": "number", "precision": 0 }
                  },
                  {
                    "fieldName": "unique_tile_clicks",
                    "displayName": "Unique Tile Clicks",
                    "scale": { "type": "quantitative" },
                    "format": { "type": "number", "precision": 0 }
                  },
                  {
                    "fieldName": "ctr",
                    "displayName": "% Home Tile Clicked vs Homepage Displayed",
                    "scale": { "type": "quantitative" },
                    "format": { "type": "percentage", "precision": 2 }
                  },
                  {
                    "fieldName": "unique_interstitial_views",
                    "displayName": "Unique Interstitial Views",
                    "scale": { "type": "quantitative" },
                    "format": { "type": "number", "precision": 0 }
                  },
                  {
                    "fieldName": "unique_interstitial_primary_button_clicks",
                    "displayName": "Unique Interstitial Primary Button Clicks",
                    "scale": { "type": "quantitative" },
                    "format": { "type": "number", "precision": 0 }
                  },
                  {
                    "fieldName": "unique_interstitial_secondary_button_clicks",
                    "displayName": "Unique Interstitial Secondary Button Clicks",
                    "scale": { "type": "quantitative" },
                    "format": { "type": "number", "precision": 0 }
                  },
                  {
                    "fieldName": "primary_button_clicked_vs_tile_displayed",
                    "displayName": "% Primary Button Clicked vs Tile Displayed",
                    "scale": { "type": "quantitative" },
                    "format": { "type": "percentage", "precision": 1 }
                  },
                  {
                    "fieldName": "secondary_button_clicked_vs_tile_displayed",
                    "displayName": "% Secondary Button Clicked vs Tile Displayed",
                    "scale": { "type": "quantitative" },
                    "format": { "type": "percentage", "precision": 1 }
                  },
                  {
                    "fieldName": "primary_button_clicked_vs_interstitial_displayed",
                    "displayName": "% Primary Button Clicked vs Interstitial Displayed",
                    "scale": { "type": "quantitative" },
                    "format": { "type": "percentage", "precision": 1 }
                  },
                  {
                    "fieldName": "secondary_button_clicked_vs_interstitial_displayed",
                    "displayName": "% Secondary Button Clicked vs Interstitial Displayed",
                    "scale": { "type": "quantitative" },
                    "format": { "type": "percentage", "precision": 1 }
                  }
                ]
              },
              "frame": {
                "title": "Home Tile CTR by Tile",
                "showTitle": true
              }
            }
          },
          "position": { "x": 0, "y": 4, "width": 12, "height": 8 }
        }
      ],
      "pageType": "PAGE_TYPE_CANVAS",
      "filters": []
    }
  ],
  "uiSettings": {
    "theme": {
      "widgetHeaderAlignment": "ALIGNMENT_UNSPECIFIED"
    }
  }
}